robot/__init__.py
robot/reservations.py
robot/robin.py
robot/user.py
tests/__init__.py
tests/constants.py
tests/reservantions_test.py
tests/robin_test.py
tests/user_test.py
robin_powered_bot-0.0.8.dist-info/LICENSE
robin_powered_bot-0.0.8.dist-info/METADATA
robin_powered_bot-0.0.8.dist-info/WHEEL
robin_powered_bot-0.0.8.dist-info/top_level.txt
robin_powered_bot-0.0.8.dist-info/RECORD
